AUTHORS
LICENSE
MANIFEST.in
README.rst
setup.cfg
setup.py
pennyblack/__init__.py
pennyblack/admin.py
pennyblack/default_settings.py
pennyblack/forms.py
pennyblack/options.py
pennyblack/tests.py
pennyblack/urls.py
pennyblack/views.py
pennyblack.egg-info/PKG-INFO
pennyblack.egg-info/SOURCES.txt
pennyblack.egg-info/dependency_links.txt
pennyblack.egg-info/top_level.txt
pennyblack/content/__init__.py
pennyblack/content/richtext.py
pennyblack/locale/de/LC_MESSAGES/django.mo
pennyblack/locale/de/LC_MESSAGES/django.po
pennyblack/locale/en/LC_MESSAGES/django.po
pennyblack/management/__init__.py
pennyblack/management/commands/__init__.py
pennyblack/management/commands/getmail.py
pennyblack/management/commands/sendmail.py
pennyblack/models/__init__.py
pennyblack/models/job.py
pennyblack/models/link.py
pennyblack/models/mail.py
pennyblack/models/newsletter.py
pennyblack/models/sender.py
pennyblack/module/__init__.py
pennyblack/module/subscriber/__init__.py
pennyblack/module/subscriber/admin.py
pennyblack/module/subscriber/forms.py
pennyblack/module/subscriber/models.py
pennyblack/module/subscriber/views.py
pennyblack/module/subscriber/fixtures/initial_data.json
pennyblack/static/pennyblack/excanvas.min.js
pennyblack/static/pennyblack/jquery.flot.min.js
pennyblack/static/pennyblack/jquery.flot.selection.min.js
pennyblack/static/pennyblack/jquery.min.js
pennyblack/templates/admin/feincms/pennyblack/newsletter/item_editor.html
pennyblack/templates/admin/pennyblack/job/change_form.html
pennyblack/templates/admin/pennyblack/job/send_confirmation.html
pennyblack/templates/admin/pennyblack/jobstatistic/change_form.html
pennyblack/templates/admin/pennyblack/jobunit/change_form.html
pennyblack/templates/admin/pennyblack/jobunit/select_receiver_collection.html
pennyblack/templates/admin/pennyblack/tiny_mce/init.html
pennyblack/templates/content/gallery/section.html
pennyblack/templates/content/image/section.html
pennyblack/templates/content/text_and_image/section.html
pennyblack/templates/content/text_only/section.html
pennyblack/templates/pennyblack/base_newsletter.html
