Metadata-Version: 1.1
Name: pennyblack
Version: 0.3.5
Summary: django based newsletter toolkit
Home-page: http://github.com/allink/pennyblack/
Author: Marc Egli
Author-email: egli@allink.ch
License: BSD License
Platform: OS Independent
Classifier: Development Status :: 3 - Alpha
Classifier: Environment :: Web Environment
Classifier: Framework :: Django
Classifier: Intended Audience :: Developers
Classifier: License :: OSI Approved :: BSD License
Classifier: Operating System :: OS Independent
Classifier: Programming Language :: Python
Classifier: Topic :: Internet :: WWW/HTTP :: Dynamic Content
Classifier: Topic :: Communications :: Email
Requires: FeinCMS(>=1.3.0)
Requires: Django(>=1.3)
Requires: pydns
Requires: pyspf
Requires: pil
